rmkf/__init__.py
rmkf/analyzer/__init__.py
rmkf/analyzer/etf_analysis.py
rmkf/downloder/__init__.py
rmkf/downloder/market_data_downloader.py
rmkf/scraper/__init__.py
rmkf/scraper/_scaper_scheme.py
rmkf/scraper/usetf_list.py
rmkf/scraper/wisdom_whale.py
rmkf-0.1.6.dist-info/METADATA
rmkf-0.1.6.dist-info/WHEEL
rmkf-0.1.6.dist-info/entry_points.txt
rmkf-0.1.6.dist-info/top_level.txt
rmkf-0.1.6.dist-info/RECORD
